citation_sorter/__init__.py
citation_sorter/citation_sorter.py
citation_sorter-0.3.2.dist-info/LICENSE
citation_sorter-0.3.2.dist-info/METADATA
citation_sorter-0.3.2.dist-info/WHEEL
citation_sorter-0.3.2.dist-info/entry_points.txt
citation_sorter-0.3.2.dist-info/top_level.txt
citation_sorter-0.3.2.dist-info/RECORD
