Metadata-Version: 2.1
Name: citation_sorter
Version: 0.3.2
Summary: CitationSorter is a Python package for sorting and organizing citations in LaTeX documents.
Home-page: https://github.com/markusbink/latex-citation-sorter
License-File: LICENSE
Requires-Dist: argparse
